dxlconsole/__init__.py
dxlconsole/__init__.pyc
dxlconsole/__main__.py
dxlconsole/_compat.py
dxlconsole/_compat.pyc
dxlconsole/_version.py
dxlconsole/_version.pyc
dxlconsole/app.py
dxlconsole/app.pyc
dxlconsole/console.html
dxlconsole/console.py
dxlconsole/console.pyc
dxlconsole/handlers.py
dxlconsole/handlers.pyc
dxlconsole/login.html
dxlconsole/module.py
dxlconsole/module.pyc
dxlconsole/util.py
dxlconsole/util.pyc
dxlconsole/_config/__init__.py
dxlconsole/_config/app/__init__.py
dxlconsole/_config/app/dxlclient.config
dxlconsole/_config/app/dxlconsole.config
dxlconsole/_config/app/logging.config
dxlconsole/_config/sample/__init__.py
dxlconsole/_config/sample/dxlclient.config
dxlconsole/modules/__init__.py
dxlconsole/modules/__init__.pyc
dxlconsole/modules/broker/__init__.py
dxlconsole/modules/broker/__init__.pyc
dxlconsole/modules/broker/content.html
dxlconsole/modules/broker/module.py
dxlconsole/modules/broker/module.pyc
dxlconsole/modules/certificates/__init__.py
dxlconsole/modules/certificates/__init__.pyc
dxlconsole/modules/certificates/content.html
dxlconsole/modules/certificates/module.py
dxlconsole/modules/certificates/module.pyc
dxlconsole/modules/monitor/__init__.py
dxlconsole/modules/monitor/__init__.pyc
dxlconsole/modules/monitor/content.html
dxlconsole/modules/monitor/messages_handler.py
dxlconsole/modules/monitor/messages_handler.pyc
dxlconsole/modules/monitor/module.py
dxlconsole/modules/monitor/module.pyc
dxlconsole/modules/monitor/send_message_handler.py
dxlconsole/modules/monitor/send_message_handler.pyc
dxlconsole/modules/monitor/services_handler.py
dxlconsole/modules/monitor/services_handler.pyc
dxlconsole/modules/monitor/subscriptions_handler.py
dxlconsole/modules/monitor/subscriptions_handler.pyc
dxlconsole/modules/monitor/websocket_handler.py
dxlconsole/modules/monitor/websocket_handler.pyc
dxlconsole/modules/topology/__init__.py
dxlconsole/modules/topology/__init__.pyc
dxlconsole/modules/topology/content.html
dxlconsole-0.3.3.dist-info/LICENSE
dxlconsole-0.3.3.dist-info/LICENSE -Base64Binary
dxlconsole-0.3.3.dist-info/METADATA
dxlconsole-0.3.3.dist-info/WHEEL
dxlconsole-0.3.3.dist-info/top_level.txt
dxlconsole-0.3.3.dist-info/RECORD
