Metadata-Version: 2.1
Name: dxlconsole
Version: 0.3.3
Summary: Web-based console for interacting with a DXL fabric
Home-page: http://www.mcafee.com
Author: McAfee LLC
License: Apache License 2.0
Keywords: opendxl,dxl,mcafee,console
Platform: UNKNOWN
Classifier: Development Status :: 4 - Beta
Classifier: Topic :: Software Development :: Libraries :: Python Modules
Classifier: License :: OSI Approved :: Apache Software License
Classifier: Programming Language :: Python
Classifier: Programming Language :: Python :: 2
Classifier: Programming Language :: Python :: 2.7
Classifier: Programming Language :: Python :: 3
Classifier: Programming Language :: Python :: 3.4
Classifier: Programming Language :: Python :: 3.5
Classifier: Programming Language :: Python :: 3.6
Classifier: Programming Language :: Python :: 3.7
Requires-Python: >=2.7.9,!=3.0.*,!=3.1.*,!=3.2.*,!=3.3.*
Requires-Dist: tornado
Requires-Dist: dxlbootstrap (>=0.1.3)
Requires-Dist: dxlclient
Requires-Dist: beautifulSoup4
Provides-Extra: dev
Requires-Dist: pylint ; extra == 'dev'
Requires-Dist: sphinx ; extra == 'dev'
Provides-Extra: test
Requires-Dist: pylint ; extra == 'test'
